Workbook

Sheet Assumptions
A1: Event Photo Database - Cloud Cost Model: Assumptions & Unit Prices
A2: All prices East US / Zone-1, USD, June 2026. Blue = input you can change. See Sources sheet for citations.
A4: SCALE ASSUMPTIONS (this org)
A5: Driver | B5: Value | C5: Unit | D5: Note
A6: Active admin users (MAU) | B6: 50 | C6: users | D6: ~50 verified admins per ARCHITECTURE.md
A7: DB reads / month | B7: 300000 | C7: reads | D7: ~10k reads/day per GCP assessment
A8: DB writes / month | B8: 30000 | C8: writes | D8: ~1k writes/day (admin edits, audit log)
A9: DB stored data | B9: 2 | C9: GB | D9: events, clubs, photos metadata, audit log
A10: Photo originals stored | B10: 100 | C10: GB | D10: primary photo library
A11: Photo egress to browsers / month | B11: 50 | C11: GB | D11: WATCH ITEM - varies with traffic
A12: API requests / month | B12: 400000 | C12: requests | D12: light, read-heavy
A13: Indexer compute / month | B13: 3 | C13: event runs | D13: Cloud Run Job / Container Apps Job bursts
A14: Matcher compute / month | B14: 30 | C14: GB-hr equiv | D14: occasional face-match queries
A16: UNIT PRICES
A17: Item | B17: Price | C17: Unit | D17: Note
A18: AZURE - Container Apps active vCPU-second | B18: 2.4e-05 | C18: $/vCPU-s | D18: after 180k free vCPU-s/mo
A19: AZURE - Container Apps active GiB-second | B19: 2.5e-06 | C19: $/GiB-s | D19: after 360k free GiB-s/mo
A20: AZURE - Container Apps requests | B20: 0.4 | C20: $/million | D20: after 2M free/mo
A21: AZURE - Cosmos DB serverless Request Units | B21: 0.25 | C21: $/million RU | D21: serverless has NO free tier
A22: AZURE - Cosmos DB serverless storage | B22: 0.25 | C22: $/GB-mo
A23: AZURE - Blob Storage hot LRS | B23: 0.018 | C23: $/GB-mo | D23: Cool ~$0.01; Cold ~$0.0036
A24: AZURE - Egress (internet, first 10 TB) | B24: 0.087 | C24: $/GB | D24: first 100 GB/mo is free
A25: AZURE - Static Web Apps (Free plan) | B25: 0 | C25: $/mo | D25: 100 GB bandwidth, free SSL+domain
A26: AZURE - Entra External ID | B26: 0 | C26: $/mo | D26: free <=50,000 MAU
A27: AZURE - Key Vault operations | B27: 0.03 | C27: $/10k ops
A28: AZURE - Container Registry (Basic) | B28: 5 | C28: $/mo | D28: fixed; 10 GB incl. (or use free GHCR)
A29: AZURE - Application Insights | B29: 0 | C29: $/mo | D29: first 5 GB ingest/mo free
A30: AZURE - Front Door Standard base | B30: 35 | C30: $/mo | D30: AVOID - not needed at this scale
A31: GCP - Cloud Run / Run Jobs | B31: 0 | C31: $/mo | D31: within always-free grant at this scale
A32: GCP - Firestore reads | B32: 0.03 | C32: $/100k
A33: GCP - Firestore writes | B33: 0.09 | C33: $/100k
A34: GCP - Firestore storage | B34: 0.18 | C34: $/GB-mo
A35: GCP - Cloud Storage Standard | B35: 0.02 | C35: $/GB-mo
A36: GCP - Egress (internet) | B36: 0.12 | C36: $/GB | D36: higher than Azure since May-2025 hike
A37: GCP - Firebase Hosting | B37: 0 | C37: $/mo | D37: free tier
A38: GCP - Secret Manager + Artifact Registry | B38: 0.16 | C38: $/mo | D38: approx fixed small

Sheet Cost Comparison
A1: GCP (target) vs Azure (proposed) - Monthly Cost at This Org's Scale
A2: List price = what you'd pay with no credit. Both clouds are effectively $0 while the nonprofit grant lasts.
A4: Layer | B4: GCP service | C4: Azure service | D4: GCP $/mo (list) | E4: Azure $/mo (list)
A5: Frontend hosting | B5: Firebase Hosting | C5: Static Web Apps (Free) | D5: =Assumptions!$B$37 -> 0 | E5: =Assumptions!$B$25 -> 0
A6: Backend API | B6: Cloud Run | C6: Container Apps (Consumption) | D6: =0 -> 0 | E6: =0 -> 0
A7: Face matcher | B7: Cloud Run | C7: Container Apps (Consumption) | D7: =0 -> 0 | E7: =0 -> 0
A8: Photo indexer | B8: Cloud Run Job | C8: Container Apps Job | D8: =0 -> 0 | E8: =0 -> 0
A9: Database | B9: Firestore | C9: Cosmos DB (serverless) | D9: =Assumptions!$B$7/100000*Assumptions!$B$32+Assumptions!$B$8/100000*Assumptions!$B$33+Assumptions!$B$9*Assumptions!$B$34 -> 0.477 | E9: =(Assumptions!$B$7*1+Assumptions!$B$8*5)/1000000*Assumptions!$B$21+Assumptions!$B$9*Assumptions!$B$22 -> 0.6125
A10: Auth | B10: Firebase Auth | C10: Entra External ID | D10: =0 -> 0 | E10: =0 -> 0
A11: Photo storage | B11: Cloud Storage | C11: Blob Storage (hot LRS) | D11: =Assumptions!$B$10*Assumptions!$B$35 -> 2 | E11: =Assumptions!$B$10*Assumptions!$B$23 -> 1.8
A12: Photo egress | B12: Cloud egress | C12: Blob egress (first 100GB free) | D12: =Assumptions!$B$11*Assumptions!$B$36 -> 6 | E12: =MAX(0,Assumptions!$B$11-100)*Assumptions!$B$24 -> 0
A13: Secrets | B13: Secret Manager | C13: Key Vault | D13: =0.06 -> 0.06 | E13: =0.05 -> 0.05
A14: Container registry | B14: Artifact Registry | C14: Container Registry (Basic) | D14: =0.1 -> 0.1 | E14: =Assumptions!$B$28 -> 5
A15: Logging / monitoring | B15: Cloud Logging | C15: Application Insights | D15: =0 -> 0 | E15: =0 -> 0
A16: TOTAL - list price (no credit) | D16: =SUM(D5:D15) -> 8.637 | E16: =SUM(E5:E15) -> 7.4625
A17: TOTAL - with nonprofit grant applied | D17: =0 -> 0 | E17: =0 -> 0
A19: Notes:
A20: Compute (API, matcher, indexer) stays inside both clouds' always-free monthly grant at this traffic.
A21: GCP grant = $10,000/yr ($833/mo). Azure grant = $2,000/yr ($167/mo). Both dwarf the list total above.
A22: Egress is the only line that scales with traffic - Azure's first 100 GB/mo is free and its per-GB rate is lower than GCP's.
A23: Cosmos serverless has NO free tier; provisioned free tier (1,000 RU/s + 25 GB) would make the DB line $0 - see Under $100 Plan.

Sheet Azure Under $100 Plan
A1: Staying Under $100/month on Azure
A2: Existing Azure spend is already $65/mo, so the NEW workload must add < $35/mo of un-credited cash.
A4: BUDGET MATH
A5: Target monthly ceiling | B5: 100
A6: Existing Azure spend (current) | B6: 65 | C6: confirm: M365 licence (NOT grant-covered) vs Azure consumption (grant-covered)
A7: Headroom for new workload | B7: =B5-B6 -> 35
A9: NEW AZURE WORKLOAD - recommended cheapest config
A10: Line item | B10: $/mo | C10: How it's kept low
A11: Static Web Apps (frontend) | B11: 0 | C11: Free plan: 100 GB bandwidth, free TLS + custom domain
A12: Container Apps: API + matcher + indexer | B12: 0 | C12: Consumption env, min-replicas=0 (scale to zero); rides 180k vCPU-s / 2M req free grant
A13: Cosmos DB | B13: 0 | C13: Use PROVISIONED free tier (1,000 RU/s + 25 GB free, 1 per subscription) instead of serverless
A14: Blob Storage (100 GB, originals in Cool) | B14: 1 | C14: Originals -> Cool/Cold tier; serve only resized derivatives from Hot; LRS not GRS
A15: Egress | B15: 0 | C15: First 100 GB/mo free; cache derivatives, never serve full-res originals to the browser
A16: Entra External ID (auth) | B16: 0 | C16: Free under 50,000 MAU
A17: Key Vault | B17: 0.05 | C17: Pay-per-op, a few cents
A18: Container Registry | B18: 0 | C18: Push images to GitHub Container Registry (free) and pull into Container Apps; or ACR Basic $5
A19: Application Insights / Log Analytics | B19: 0 | C19: First 5 GB ingest/mo free; set 5 GB daily cap
A20: Front Door / CDN | B20: 0 | C20: DO NOT provision Front Door Standard ($35/mo base) - use Static Web Apps' built-in CDN
A21: NEW workload subtotal (list, no grant) | B21: =SUM(B11:B20) -> 1.05
A22: NEW workload after $2,000/yr grant ($167/mo) | B22: =0 -> 0 | C22: grant covers it ~80x over
A23: TOTAL monthly cash (existing + new, list) | B23: =B6+B21 -> 66.05 | C23: =IF(B23<=B5,"UNDER $100 - OK","OVER - cut levers") -> UNDER $100 - OK
A25: GRANT RUNWAY
A26: Annual grant | B26: 2000
A27: New workload annual list cost | B27: =B21*12 -> 12.6
A28: Grant covers new workload for | B28: =IF(B21=0,999,B26/B21) -> 1904.7619
A30: GUARDRAILS TO SET ON DAY 1
A31: - Azure Cost Management budget alert at $80/mo with 50/80/100% email thresholds.
A32: - Cost anomaly alert enabled (catches egress spikes - the classic nonprofit billing surprise).
A33: - Container Apps: max-replicas capped (e.g. 5) and min-replicas=0 on every app.
A34: - Storage: serve via SAS URLs with cache headers; lifecycle rule moves originals to Cool after 30 days.
A35: - Log Analytics daily cap = 5 GB so Application Insights ingest can't run away.

Sheet Sources
A1: Pricing Sources (accessed June 2026)
A3: Azure Container Apps pricing | B3: https://azure.microsoft.com/en-us/pricing/details/container-apps/
A4: Azure Cosmos DB serverless pricing | B4: https://azure.microsoft.com/en-us/pricing/details/cosmos-db/serverless/
A5: Azure Cosmos DB lifetime free tier | B5: https://learn.microsoft.com/en-us/azure/cosmos-db/free-tier
A6: Azure Blob Storage pricing | B6: https://azure.microsoft.com/en-us/pricing/details/storage/blobs/
A7: Azure bandwidth / egress pricing | B7: https://azure.microsoft.com/en-us/pricing/details/bandwidth/
A8: Azure Static Web Apps pricing | B8: https://azure.microsoft.com/en-us/pricing/details/app-service/static/
A9: Microsoft Entra External ID pricing | B9: https://azure.microsoft.com/en-us/pricing/details/microsoft-entra-external-id/
A10: Azure Key Vault pricing | B10: https://azure.microsoft.com/en-us/pricing/details/key-vault/
A11: Azure Container Registry pricing | B11: https://azure.microsoft.com/en-us/pricing/details/container-registry/
A12: Microsoft for Nonprofits - Azure grant ($2,000/yr) | B12: https://learn.microsoft.com/en-us/industry/nonprofit/microsoft-for-nonprofits/claim-activate-nonprofit-azure-grant
A13: Google Cloud Storage pricing | B13: https://cloud.google.com/storage/pricing
A14: Firestore pricing | B14: https://cloud.google.com/firestore/pricing
A15: GCP nonprofit credit ($10,000/yr) - internal UX_AND_GCP_ASSESSMENT.md | B15: (repo)
